hack4you/__init__.py
hack4you/courses.py
hack4you/utils.py
HolaCabezon-0.1.0.dist-info/METADATA
HolaCabezon-0.1.0.dist-info/WHEEL
HolaCabezon-0.1.0.dist-info/top_level.txt
HolaCabezon-0.1.0.dist-info/RECORD
