Metadata-Version: 2.1
Name: HolaCabezon
Version: 0.1.0
Summary: Search course in hack4you academy
Home-page: https://hack4u.io
Author: Pepito Chulo
